thornode_py/__init__.py
thornode_py/thornode_api.py
thornode_py/models/__init__.py
thornode_py/models/thronode_models_auth.py
thornode_py/models/thronode_models_bank.py
thornode_py/models/thronode_models_block.py
thornode_py/models/thronode_models_borrower.py
thornode_py/models/thronode_models_health.py
thornode_py/models/thronode_models_invariant.py
thornode_py/models/thronode_models_liquidiry_provider.py
thornode_py/models/thronode_models_network.py
thornode_py/models/thronode_models_node.py
thornode_py/models/thronode_models_oracle.py
thornode_py/models/thronode_models_pool.py
thornode_py/models/thronode_models_pool_slip.py
thornode_py/models/thronode_models_queue.py
thornode_py/models/thronode_models_quote.py
thornode_py/models/thronode_models_rune_pool.py
thornode_py/models/thronode_models_saver.py
thornode_py/models/thronode_models_secured_asset.py
thornode_py/models/thronode_models_streaming_swap.py
thornode_py/models/thronode_models_swap.py
thornode_py/models/thronode_models_tcy_claimer.py
thornode_py/models/thronode_models_tcy_staker.py
thornode_py/models/thronode_models_thorname.py
thornode_py/models/thronode_models_trade_unit.py
thornode_py/models/thronode_models_transaction.py
thornode_py/models/thronode_models_vault.py
thornode_py/tests/__init__.py
thornode_py/tests/test_auth.py
thornode_py/tests/test_bank.py
thornode_py/tests/test_block.py
thornode_py/tests/test_borrower.py
thornode_py/tests/test_health.py
thornode_py/tests/test_invariants.py
thornode_py/tests/test_liquidity_provider.py
thornode_py/tests/test_network.py
thornode_py/tests/test_node.py
thornode_py/tests/test_oracle.py
thornode_py/tests/test_pool.py
thornode_py/tests/test_pool_slip.py
thornode_py/tests/test_queue.py
thornode_py/tests/test_quote.py
thornode_py/tests/test_rune_pool.py
thornode_py/tests/test_saver.py
thornode_py/tests/test_secured_asset.py
thornode_py/tests/test_streaming_swap.py
thornode_py/tests/test_swap.py
thornode_py/tests/test_tcy_claimer.py
thornode_py-0.0.3.dist-info/LICENSE.txt
thornode_py-0.0.3.dist-info/METADATA
thornode_py-0.0.3.dist-info/WHEEL
thornode_py-0.0.3.dist-info/top_level.txt
thornode_py-0.0.3.dist-info/RECORD
