Metadata-Version: 2.1
Name: thornode-py
Version: 0.0.3
Summary: Python client for THORNode API
Home-page: https://github.com/jpleorx/thornode-py
Author: Leo Ertuna
Author-email: leo.ertuna@gmail.com
License: Creative Commons Attribution-NonCommercial-NoDerivatives 4.0 International Public License
Download-URL: https://pypi.org/project/thornode-py/
Platform: UNKNOWN
License-File: LICENSE.txt
Requires-Dist: pydantic
Requires-Dist: requests
